translate6frames/__init__.py
translate6frames/translate6frames.py
translate6frames-0.1.3.dist-info/METADATA
translate6frames-0.1.3.dist-info/WHEEL
translate6frames-0.1.3.dist-info/top_level.txt
translate6frames-0.1.3.dist-info/RECORD
