Metadata-Version: 2.1
Name: translate6frames
Version: 0.1.3
Summary: translate genes RNA/DNA to proteins (all 6 frames)
Home-page: https://github.com/khaledianehdieh/translate6frames
Author: Ehdieh Khaledian
Author-email: khaledianehdieh@gmail.com
License: MIT
Download-URL: https://pypi.org/project/translate6frames/
Keywords: Translate genes,6 frame,gene to protein,python DNA to protein,python,RNA to protein
Platform: UNKNOWN
